hugchat/__init__.py
hugchat/cli.py
hugchat/exceptions.py
hugchat/hugchat.py
hugchat/login.py
hugchat/message.py
hugchat/types/assistant.py
hugchat/types/file.py
hugchat/types/message.py
hugchat/types/model.py
hugchat/types/tool.py
hugchat-0.5.0.dist-info/licenses/LICENSE
hugchat-0.5.0.dist-info/METADATA
hugchat-0.5.0.dist-info/WHEEL
hugchat-0.5.0.dist-info/top_level.txt
hugchat-0.5.0.dist-info/RECORD
